RxjavaWendangZhongwenbanFix1/README.md
RxjavaWendangZhongwenbanFix1/__init__.py
RxjavaWendangZhongwenbanFix1/__main__.py
RxjavaWendangZhongwenbanFix1/file.epub
RxjavaWendangZhongwenbanFix1/index.html
RxjavaWendangZhongwenbanFix1/css/__init__.py
RxjavaWendangZhongwenbanFix1/css/annotations.css
RxjavaWendangZhongwenbanFix1/css/main.css
RxjavaWendangZhongwenbanFix1/css/normalize.css
RxjavaWendangZhongwenbanFix1/css/popup.css
RxjavaWendangZhongwenbanFix1/font/__init__.py
RxjavaWendangZhongwenbanFix1/font/fontello.eot
RxjavaWendangZhongwenbanFix1/font/fontello.svg
RxjavaWendangZhongwenbanFix1/font/fontello.ttf
RxjavaWendangZhongwenbanFix1/font/fontello.woff
RxjavaWendangZhongwenbanFix1/img/__init__.py
RxjavaWendangZhongwenbanFix1/img/annotator-glyph-sprite.png
RxjavaWendangZhongwenbanFix1/img/annotator-icon-sprite.png
RxjavaWendangZhongwenbanFix1/img/apple-touch-icon.png
RxjavaWendangZhongwenbanFix1/img/cancelfullscreen.png
RxjavaWendangZhongwenbanFix1/img/close.png
RxjavaWendangZhongwenbanFix1/img/fullscreen.png
RxjavaWendangZhongwenbanFix1/img/loader.gif
RxjavaWendangZhongwenbanFix1/img/menu-icon.png
RxjavaWendangZhongwenbanFix1/img/save.png
RxjavaWendangZhongwenbanFix1/img/saved.png
RxjavaWendangZhongwenbanFix1/img/settings-s.png
RxjavaWendangZhongwenbanFix1/img/settings.png
RxjavaWendangZhongwenbanFix1/img/star.png
RxjavaWendangZhongwenbanFix1/js/__init__.py
RxjavaWendangZhongwenbanFix1/js/epub.js
RxjavaWendangZhongwenbanFix1/js/epub.min.js
RxjavaWendangZhongwenbanFix1/js/epub.min.map
RxjavaWendangZhongwenbanFix1/js/hooks.min.js
RxjavaWendangZhongwenbanFix1/js/hooks.min.map
RxjavaWendangZhongwenbanFix1/js/reader.js
RxjavaWendangZhongwenbanFix1/js/reader.js.map
RxjavaWendangZhongwenbanFix1/js/reader.min.js
RxjavaWendangZhongwenbanFix1/js/reader.min.map
RxjavaWendangZhongwenbanFix1/js/hooks/__init__.py
RxjavaWendangZhongwenbanFix1/js/hooks/extensions/__init__.py
RxjavaWendangZhongwenbanFix1/js/hooks/extensions/highlight.js
rxjava_wendang_zhongwenban_fix1-2024.3.1.0.dist-info/METADATA
rxjava_wendang_zhongwenban_fix1-2024.3.1.0.dist-info/WHEEL
rxjava_wendang_zhongwenban_fix1-2024.3.1.0.dist-info/entry_points.txt
rxjava_wendang_zhongwenban_fix1-2024.3.1.0.dist-info/top_level.txt
rxjava_wendang_zhongwenban_fix1-2024.3.1.0.dist-info/RECORD
